aws_ssh/__init__.py
aws_ssh/aws.py
aws_ssh/cli.py
aws_ssh/errors.py
aws_ssh/interfaces.py
aws_ssh-0.0.2.data/scripts/aws-ssh
aws_ssh-0.0.2.data/scripts/awssh
aws_ssh-0.0.2.data/scripts/ssh-ec2
aws_ssh-0.0.2.dist-info/METADATA
aws_ssh-0.0.2.dist-info/RECORD
aws_ssh-0.0.2.dist-info/WHEEL
aws_ssh-0.0.2.dist-info/entry_points.txt
aws_ssh-0.0.2.dist-info/top_level.txt
aws_ssh-0.0.2.dist-info/zip-safe
