Metadata-Version: 2.1
Name: aws-ssh
Version: 0.0.2
Summary: A utility to enable easy SSH connections to AWS EC2 instances.
Home-page: https://github.com/arusahni/aws-ssh
Author: Aru Sahni
Author-email: arusahni@gmail.com
License: MIT
Keywords: aws ssh ec2 iam amazon web services remote
Platform: UNKNOWN
Classifier: Development Status :: 3 - Alpha
Classifier: Environment :: Console
Classifier: Intended Audience :: Developers
Classifier: Intended Audience :: System Administrators
Classifier: License :: OSI Approved :: MIT License
Classifier: Programming Language :: Python :: 3
Classifier: Topic :: System :: Systems Administration
Provides-Extra: dev
Requires-Dist: boto3
Requires-Dist: pexpect
Requires-Dist: six
Requires-Dist: tqdm
Provides-Extra: dev
Requires-Dist: mock; extra == 'dev'
Requires-Dist: pytest; extra == 'dev'
Requires-Dist: coverage; extra == 'dev'
Requires-Dist: pylint; extra == 'dev'
Requires-Dist: pytest-cov; extra == 'dev'
Requires-Dist: pypandoc; extra == 'dev'
